[
  {
    "type": "Feature",
    "geometry": {
      "type": "Point",
      "modType": "Orchestra",
      "coordinates": {
        "lat": 39.95270111977888, 
        "lon": -75.13972703050233
      }
    },
    "properties": {
      "name": "Cherry Street Pier",
      "address": "121 N Christopher Columbus Blvd",
      "module": "Orchestra",
      "facts": [
        {"fact": "City Hall was the tallest habitable building in the world from 1894 to 1908."},
        {"fact": "The 5.5 mile Delaware River Trail project connects to the Cherry Street Peer."},
        {"fact": "Cherry Street Peer houses close to a dozen artist studios in addition to an outdoor restaurant and bar and open performance venue."}
      ],
      "question": "A transparent space open to all, a framework on the water.  ",
      "statement": "The first public home of the Public Orchestra of Philadelphia."
    }
  }
]